Metadata-Version: 2.4
Name: h1d
Version: 0.2.12
Summary: HiC1Dmetrics pip version
Home-page: https://github.com/wangjk321/HiC1Dmetrics
Author: wangjiankng
Author-email: wangjk321@gmail.com
Classifier: Programming Language :: Python :: 3
Classifier: License :: OSI Approved :: GNU General Public License v3 (GPLv3)
Classifier: Operating System :: OS Independent
Requires-Dist: pandas
Requires-Dist: numpy
Requires-Dist: scikit-learn
Requires-Dist: scipy
Requires-Dist: matplotlib
Requires-Dist: seaborn
Requires-Dist: multiprocess
Requires-Dist: fithic==2.0.7
Requires-Dist: statsmodels
Requires-Dist: cooler==0.9.*
Dynamic: author
Dynamic: author-email
Dynamic: classifier
Dynamic: description
Dynamic: description-content-type
Dynamic: home-page
Dynamic: requires-dist
Dynamic: summary
